Workbook

Sheet Leeme
A1: Costeo del MVP · Desafío Marley Coffee
A2: Presupuesto construido de abajo hacia arriba y punto de equilibrio. Preparado para la reunión del miércoles.
A5: CÓMO ESTÁ ARMADO
A6: Supuestos | B6: Todas las tarifas, precios y volúmenes, cada uno con su fuente. Es la única hoja que hay que tocar.
A7: Costeo | B7: Cada línea es cantidad × precio unitario. Los precios vienen de Supuestos; las horas son estimación del equipo.
A8: Resumen | B8: Inversión inicial y costo recurrente por bloque, año 1 y año 2, contra el presupuesto comprometido.
A9: Equilibrio | B9: Cuánto margen debe dejar cada punto recuperado para que el plan se pague. Tiene una celda para el dato real.
A11: CÓDIGO DE COLORES
A12: Texto azul | B12: Entrada editable. Cambiarla recalcula todo el libro.
A13: Texto negro | B13: Fórmula. No editar.
A14: Texto verde | B14: Vínculo a otra hoja. No editar.
A15: Fondo amarillo | B15: Supuesto clave, o celda que debe completar Marley.
A17: MARCAS DE FUENTE
A18: [C] | B18: Dato del caso.
A19: [P] | B19: Precio público de mercado, con fuente y fecha.
A20: [D] | B20: Derivación aritmética sobre [C] o [P].
A21: [S] | B21: Supuesto del equipo. Es lo primero que conviene discutir.
A23: LO QUE ESTE LIBRO NO HACE
A24: Ventas en pesos | B24: El caso no entrega ventas, precio, ticket ni margen en pesos, y no existe una cifra pública de Chile. Por eso el impacto se mide como punto de equilibrio y no como ROI.
A25: Tarifa de agencia | B25: Se usa tarifa freelance: el costeo es un piso. Una agencia cobra más.

Sheet Supuestos
A1: Supuestos
A2: Texto azul = editable. Cada valor lleva su fuente. Cambiar un valor acá recalcula Costeo, Resumen y Equilibrio.
A4: Parámetro | B4: Valor | C4: Unidad | D4: Fuente
A5: TARIFAS DE DESARROLLO
A6: Desarrollador junior | B6: 30000 | C6: CLP / hora | D6: [P] Apollo.TI, guía 2026: CLP 25.000–35.000/h
A7: Desarrollador semi-senior | B7: 45000 | C7: CLP / hora | D7: [P] Apollo.TI, guía 2026: CLP 35.000–55.000/h
A8: Desarrollador senior | B8: 65000 | C8: CLP / hora | D8: [P] Apollo.TI, guía 2026: CLP 55.000–80.000/h
A9: Mantención anual de integraciones | B9: 0.175 | C9: % del desarrollo | D9: [P] Apollo.TI: regla de mercado 15–20% anual. Se usa el punto medio
A10: PLATAFORMA Y LICENCIAS
A11: Plataforma BSP de WhatsApp | B11: 26100 | C11: CLP / mes | D11: [P] ChatDaddy 2026, plan de entrada. Es un piso: otros proveedores cobran más
A12: Mensaje de utilidad de WhatsApp | B12: 8.1 | C12: CLP / mensaje | D12: [P] Meta, tarifa Chile 2026: CLP 5,4–8,1. Se usa el techo
A13: Mensaje de servicio (ventana de 24 h) | B13: 0 | C13: CLP / mensaje | D13: [P] Meta: sin cobro dentro de la ventana de servicio. El pedido lo inicia el cliente
A14: Licencia de CRM | B14: 20 | C14: USD / usuario / mes | D14: [P] HubSpot Sales Hub Starter, G2 y Apexure, sep-2026
A15: Usuarios de CRM | B15: 5 | C15: usuarios | D15: [S] comercial B2B, analista de datos, 2 coordinadoras, líder de proyecto
A16: Licencia de visualización | B16: 0 | C16: CLP / mes | D16: [P] Looker Studio: sin costo de licencia en uso estándar
A17: MACRO
A18: Dólar observado | B18: 925.65 | C18: CLP / USD | D18: [P] 9-sep-2026, Banco Central vía dolaronline.cl
A19: VOLUMEN
A20: Puntos Horeca activos | B20: 1150 | C20: puntos | D20: [C] Base del caso
A21: Meta de reposición digital Horeca | B21: 0.4 | C21: % de puntos | D21: [C] Meta oficial a 12 meses
A22: Puntos en el canal instrumentado al mes 12 | B22: =ROUND(B20*B21,0) -> 460 | C22: puntos | D22: [D] Puntos Horeca × meta digital
A23: Pedidos por punto al año | B23: 12 | C23: pedidos | D23: [S] Supuesto S-17 del informe: reposición mensual
A24: Mensajes de utilidad por pedido | B24: 3 | C24: mensajes | D24: [S] Confirmación, despacho y entrega
A25: RETENCIÓN Y EQUILIBRIO
A26: Retención Horeca actual | B26: 0.86 | C26: % | D26: [C] Línea base del caso
A27: Retención Horeca meta | B27: 0.9 | C27: % | D27: [C] Meta oficial a 12 meses
A28: Puntos recuperados por año | B28: =ROUND(B20*(B27-B26),0) -> 46 | C28: puntos equivalentes | D28: [D] El caso mide retención sobre clientes: es una equivalencia en puntos
A29: Factor de gradualidad del año 1 | B29: 0.5 | C29: fracción del año | D29: [S] La mejora opera de forma progresiva: en promedio, medio año de efecto
A30: PRESUPUESTO
A31: Contingencia | B31: 0.1 | C31: % del subtotal | D31: [S] Práctica de mercado en proyectos de software
A32: Presupuesto máximo del caso | B32: 220000000 | C32: CLP, sin IVA | D32: [C] §3.6 del caso, primeros 12 meses
A33: Presupuesto comprometido del informe | B33: 83600000 | C33: CLP, sin IVA | D33: [C] Informe Final, tabla de presupuesto: 38% del total

Sheet Costeo
A1: Costeo de abajo hacia arriba
A2: Cada línea es cantidad × precio unitario. Horas en azul = estimación del equipo, editable. Precios en verde = vienen de Supuestos.
A4: Bloque | B4: Ítem | C4: Cantidad | D4: Unidad | E4: Precio unitario (CLP) | F4: Total año 1 (CLP) | G4: Total año 2 (CLP) | H4: Tipo | I4: Etapa | J4: Base
A5: B1 | B5: Depuración y carga del maestro de puntos Horeca | C5: 80 | D5: horas | E5: =Supuestos!$B$7 -> 45000 | F5: =C5*E5 -> 3600000 | G5: 0 | H5: Inicial | I5: Fase 0 · sem 1–6 | J5: Completitud actual 26%: faltan ~850 fichas por completar
A6: B2 | B6: Diseño del modelo de datos y de las vistas | C6: 60 | D6: horas | E6: =Supuestos!$B$8 -> 65000 | F6: =C6*E6 -> 3900000 | G6: 0 | H6: Inicial | I6: Fase 0 | J6: Define qué se ve por punto, por canal y por alerta
A7: B2 | B7: Construcción del tablero centralizado | C7: 100 | D7: horas | E7: =Supuestos!$B$7 -> 45000 | F7: =C7*E7 -> 4500000 | G7: 0 | H7: Inicial | I7: Fase 0 → Corto | J7: Consola interna: dato consolidado, reglas y vista por punto
A8: B2 | B8: Licencia de visualización | C8: 12 | D8: meses | E8: =Supuestos!$B$16 -> 0 | F8: =C8*E8 -> 0 | G8: =12*E8 -> 0 | H8: Recurrente | I8: Continuo | J8: Looker Studio sin costo; si se elige Power BI, cambiar en Supuestos
A9: LE1 | B9: Diseño del flujo conversacional de pedido | C9: 60 | D9: horas | E9: =Supuestos!$B$7 -> 45000 | F9: =C9*E9 -> 2700000 | G9: 0 | H9: Inicial | I9: Corto · mes 2 | J9: El cliente pide igual que hoy; el pedido queda como objeto con estado
A10: LE1 | B10: Integración WhatsApp ↔ CRM | C10: 120 | D10: horas | E10: =Supuestos!$B$7 -> 45000 | F10: =C10*E10 -> 5400000 | G10: 0 | H10: Inicial | I10: Corto · mes 2–3 | J10: Cada conversación de pedido crea un registro vinculado al punto
A11: LE1 | B11: Integración CRM ↔ ERP (estado de pedido) | C11: 160 | D11: horas | E11: =Supuestos!$B$8 -> 65000 | F11: =C11*E11 -> 10400000 | G11: 0 | H11: Inicial | I11: Corto · mes 2–4 | J11: La pieza más compleja: el ERP no identifica el punto físico
A12: LE1 | B12: Pruebas y ajuste en el piloto de 36 puntos | C12: 80 | D12: horas | E12: =Supuestos!$B$7 -> 45000 | F12: =C12*E12 -> 3600000 | G12: 0 | H12: Inicial | I12: Corto · mes 4 | J12: 20 Horeca · 10 panaderías independientes · 6 OCS directos
A13: LE1 | B13: Plataforma BSP de WhatsApp | C13: 12 | D13: meses | E13: =Supuestos!$B$11 -> 26100 | F13: =C13*E13 -> 313200 | G13: =12*E13 -> 313200 | H13: Recurrente | I13: Continuo | J13: Proveedor autorizado de la API de WhatsApp Business
A14: LE1 | B14: Mensajes de utilidad fuera de la ventana de 24 h | C14: =Supuestos!$B$22*Supuestos!$B$23*Supuestos!$B$24 -> 16560 | D14: mensajes | E14: =Supuestos!$B$12 -> 8.1 | F14: =C14*E14 -> 134136 | G14: =C14*E14 -> 134136 | H14: Recurrente | I14: Continuo | J14: Puntos del canal × pedidos × mensajes. Los de servicio no se cobran
A15: LE1 | B15: Licencias de CRM | C15: =Supuestos!$B$15*12 -> 60 | D15: usuario-mes | E15: =Supuestos!$B$14*Supuestos!$B$18 -> 18513 | F15: =C15*E15 -> 1110780 | G15: =C15*E15 -> 1110780 | H15: Recurrente | I15: Continuo | J15: Si el CRM actual de Marley lo soporta, esta línea desaparece
A16: LE1 | B16: Mantención de las integraciones | C16: 9 | D16: meses | E16: =(F10+F11)*Supuestos!$B$9/12 -> 230416.67 | F16: =C16*E16 -> 2073750 | G16: =12*E16 -> 2765000 | H16: Recurrente | I16: Desde mes 4 | J16: Sobre el costo de las dos integraciones. Año 1: 9 meses
A17: LE2 | B17: Diseño de la regla acumulativa (Punto de Ebullición) | C17: 40 | D17: horas | E17: =Supuestos!$B$8 -> 65000 | F17: =C17*E17 -> 2600000 | G17: 0 | H17: Inicial | I17: Mediano · mes 5 | J17: Qué eventos suman, cuánto pesa cada uno y dónde está el umbral
A18: LE2 | B18: Implementación de reglas y alertas en el tablero | C18: 80 | D18: horas | E18: =Supuestos!$B$7 -> 45000 | F18: =C18*E18 -> 3600000 | G18: 0 | H18: Inicial | I18: Mediano · mes 5–6 | J18: Opera sobre B2: sin tablero, la regla no tiene dónde verse
A19: LE2 | B19: Calibración del umbral con el historial del piloto | C19: 40 | D19: horas | E19: =Supuestos!$B$8 -> 65000 | F19: =C19*E19 -> 2600000 | G19: 0 | H19: Inicial | I19: Mediano · mes 7–8 | J19: Requiere al menos cuatro meses de pedidos registrados
A20: LE4 | B20: Diseño de la plantilla homologada de terceros | C20: 24 | D20: horas | E20: =Supuestos!$B$7 -> 45000 | F20: =C20*E20 -> 1080000 | G20: 0 | H20: Inicial | I20: Fase 0 · sem 2–6 | J20: Formato mínimo: id de punto, RUT, fecha, producto, cantidad
A21: LE4 | B21: Consolidación mensual de envíos de terceros | C21: =12*8 -> 96 | D21: horas | E21: =Supuestos!$B$6 -> 30000 | F21: =C21*E21 -> 2880000 | G21: =C21*E21 -> 2880000 | H21: Recurrente | I21: Continuo | J21: 8 horas al mes para 840 puntos operados por terceros
A22: MED | B22: Diseño del piloto y del grupo de comparación | C22: 40 | D22: horas | E22: =Supuestos!$B$8 -> 65000 | F22: =C22*E22 -> 2600000 | G22: 0 | H22: Inicial | I22: Fase 0 | J22: Línea base y criterios de escalar, corregir o detener
A24: SUBTOTAL | F24: =SUM(F5:F22) -> 53091866 | G24: =SUM(G5:G22) -> 7203116
A25: CONTINGENCIA | E25: =Supuestos!$B$31 -> 0.1 | F25: =F24*E25 -> 5309186.6 | G25: =G24*E25 -> 720311.6
A26: TOTAL | F26: =F24+F25 -> 58401053 | G26: =G24+G25 -> 7923427.6
A28: RECURSOS INTERNOS · no se imputan al presupuesto [C] §3.6 del caso
B29: Sponsor ejecutivo | C29: 10% de dedicación
B30: Líder de proyecto de marketing | C30: 50% de dedicación
B31: Responsable comercial B2B | C31: 100% de dedicación
B32: Analista de datos | C32: 50% de dedicación
A34: NO COSTEADO · se declara, no se estima
B35: Gestión del cambio y capacitación | C35: El caso exige financiarla. No hay tarifa de referencia verificada.
B36: Investigación primaria con decisores | C36: Se asume ejecutada por el equipo interno.
B37: Asesoría legal: cláusula de datos con terceros | C37: Ley 21.719. Sin tarifa de referencia verificada.
B38: Diferencial agencia vs. freelance | C38: Este costeo usa tarifa freelance: es un piso, no un techo.

Sheet Resumen
A1: Resumen del costeo
A2: Inversión inicial y costo recurrente por bloque. Todo se calcula desde Costeo.
A4: Bloque | B4: Qué es | C4: Inversión inicial | D4: Recurrente año 1 | E4: Total año 1 | F4: Recurrente año 2 | G4: % del año 1
A5: B1 | B5: Identidad de punto | C5: =SUMIFS(Costeo!$F$5:$F$22,Costeo!$A$5:$A$22,A5,Costeo!$H$5:$H$22,"Inicial") -> 3600000 | D5: =SUMIFS(Costeo!$F$5:$F$22,Costeo!$A$5:$A$22,A5,Costeo!$H$5:$H$22,"Recurrente") -> 0 | E5: =C5+D5 -> 3600000 | F5: =SUMIFS(Costeo!$G$5:$G$22,Costeo!$A$5:$A$22,A5) -> 0 | G5: =IFERROR(E5/$E$13,0) -> 0.061642725
A6: B2 | B6: Tablero centralizado | C6: =SUMIFS(Costeo!$F$5:$F$22,Costeo!$A$5:$A$22,A6,Costeo!$H$5:$H$22,"Inicial") -> 8400000 | D6: =SUMIFS(Costeo!$F$5:$F$22,Costeo!$A$5:$A$22,A6,Costeo!$H$5:$H$22,"Recurrente") -> 0 | E6: =C6+D6 -> 8400000 | F6: =SUMIFS(Costeo!$G$5:$G$22,Costeo!$A$5:$A$22,A6) -> 0 | G6: =IFERROR(E6/$E$13,0) -> 0.14383302
A7: LE1 | B7: Instrumentar la reposición | C7: =SUMIFS(Costeo!$F$5:$F$22,Costeo!$A$5:$A$22,A7,Costeo!$H$5:$H$22,"Inicial") -> 22100000 | D7: =SUMIFS(Costeo!$F$5:$F$22,Costeo!$A$5:$A$22,A7,Costeo!$H$5:$H$22,"Recurrente") -> 3631866 | E7: =C7+D7 -> 25731866 | F7: =SUMIFS(Costeo!$G$5:$G$22,Costeo!$A$5:$A$22,A7) -> 4323116 | G7: =IFERROR(E7/$E$13,0) -> 0.4406062
A8: LE2 | B8: Anticipar por acumulación | C8: =SUMIFS(Costeo!$F$5:$F$22,Costeo!$A$5:$A$22,A8,Costeo!$H$5:$H$22,"Inicial") -> 8800000 | D8: =SUMIFS(Costeo!$F$5:$F$22,Costeo!$A$5:$A$22,A8,Costeo!$H$5:$H$22,"Recurrente") -> 0 | E8: =C8+D8 -> 8800000 | F8: =SUMIFS(Costeo!$G$5:$G$22,Costeo!$A$5:$A$22,A8) -> 0 | G8: =IFERROR(E8/$E$13,0) -> 0.15068222
A9: LE4 | B9: Dato con terceros | C9: =SUMIFS(Costeo!$F$5:$F$22,Costeo!$A$5:$A$22,A9,Costeo!$H$5:$H$22,"Inicial") -> 1080000 | D9: =SUMIFS(Costeo!$F$5:$F$22,Costeo!$A$5:$A$22,A9,Costeo!$H$5:$H$22,"Recurrente") -> 2880000 | E9: =C9+D9 -> 3960000 | F9: =SUMIFS(Costeo!$G$5:$G$22,Costeo!$A$5:$A$22,A9) -> 2880000 | G9: =IFERROR(E9/$E$13,0) -> 0.067806997
A10: MED | B10: Medición del piloto | C10: =SUMIFS(Costeo!$F$5:$F$22,Costeo!$A$5:$A$22,A10,Costeo!$H$5:$H$22,"Inicial") -> 2600000 | D10: =SUMIFS(Costeo!$F$5:$F$22,Costeo!$A$5:$A$22,A10,Costeo!$H$5:$H$22,"Recurrente") -> 0 | E10: =C10+D10 -> 2600000 | F10: =SUMIFS(Costeo!$G$5:$G$22,Costeo!$A$5:$A$22,A10) -> 0 | G10: =IFERROR(E10/$E$13,0) -> 0.044519746
A11: SUBTOTAL | C11: =SUM(C5:C10) -> 46580000 | D11: =SUM(D5:D10) -> 6511866 | E11: =SUM(E5:E10) -> 53091866 | F11: =SUM(F5:F10) -> 7203116 | G11: =IFERROR(E11/$E$13,0) -> 0.90909091
A12: CONTINGENCIA | C12: =C11*Supuestos!$B$31 -> 4658000 | D12: =D11*Supuestos!$B$31 -> 651186.6 | E12: =E11*Supuestos!$B$31 -> 5309186.6 | F12: =F11*Supuestos!$B$31 -> 720311.6 | G12: =IFERROR(E12/$E$13,0) -> 0.090909091
A13: TOTAL | C13: =C11+C12 -> 51238000 | D13: =D11+D12 -> 7163052.6 | E13: =E11+E12 -> 58401053 | F13: =F11+F12 -> 7923427.6 | G13: =IFERROR(E13/$E$13,0) -> 1
A15: CONTRA EL PRESUPUESTO
B16: Costeo de abajo hacia arriba · año 1 | E16: =E13 -> 58401053
B17: Presupuesto comprometido en el informe | E17: =Supuestos!$B$33 -> 83600000
B18: Holgura del comprometido sobre el costeo | E18: =E17-E16 -> 25198947
B19: El comprometido equivale a | E19: =IFERROR(E17/E16,0) -> 1.431481
B20: Costeo como % del presupuesto del caso | E20: =IFERROR(E16/Supuestos!$B$32,0) -> 0.26545933
B21: Comprometido como % del presupuesto del caso | E21: =IFERROR(E17/Supuestos!$B$32,0) -> 0.38
B22: La holgura cubre lo que no se pudo costear con fuente: gestión del cambio, capacitación, asesoría legal y el diferencial de tarifa entre agencia y freelance.

Sheet Equilibrio
A1: Punto de equilibrio
A2: Cuánto margen tiene que dejar al mes cada punto Horeca que se deja de perder, para que el plan se pague. No requiere conocer las ventas de Marley.
A4: PUNTOS RECUPERADOS
A5: Puntos Horeca activos | B5: =Supuestos!B20 -> 1150
A6: Retención actual | B6: =Supuestos!B26 -> 0.86
A7: Retención meta | B7: =Supuestos!B27 -> 0.9
A8: Puntos recuperados por año | B8: =Supuestos!B28 -> 46
A9: Factor de gradualidad del año 1 | B9: =Supuestos!B29 -> 0.5
A10: Puntos-año recuperados · año 1 | B10: =B8*B9 -> 23
A11: Puntos-año recuperados · año 2 | B11: =B8+B8*B9 -> 69
A12: Puntos-año recuperados · 24 meses | B12: =B10+B11 -> 92
A13: Año 2 suma los puntos salvados en el año 1, que siguen comprando, más medio año de los que se salvan en el año 2.
A15: COSTO DEL PLAN
B16: Costeo (piso) | C16: Comprometido (informe)
A17: Costo a 12 meses | B17: =Resumen!E13 -> 58401053 | C17: =Supuestos!B33 -> 83600000
A18: Costo a 24 meses | B18: =Resumen!E13+Resumen!F13 -> 66324480 | C18: =Supuestos!B33+Resumen!F13 -> 91523428
A20: MARGEN MÍNIMO MENSUAL POR PUNTO RECUPERADO
A21: Escenario | B21: Costeo (piso) | C21: Comprometido (informe)
A22: A 12 meses · la mejora opera de forma gradual | B22: =IFERROR(B17/($B$10*12),0) -> 211598.02 | C22: =IFERROR(C17/($B$10*12),0) -> 302898.55
A23: A 12 meses · la mejora opera desde el día uno | B23: =IFERROR(B17/($B$8*12),0) -> 105799.01 | C23: =IFERROR(C17/($B$8*12),0) -> 151449.28
A24: A 24 meses · la mejora opera de forma gradual | B24: =IFERROR(B18/($B$12*12),0) -> 60076.522 | C24: =IFERROR(C18/($B$12*12),0) -> 82901.655
A25: Lectura: para que el plan se pague, cada punto Horeca que se deja de perder debe dejar al menos ese margen de contribución al mes. La fila de 24 meses es la que corresponde a una inversión en capacidad, porque el costo inicial se paga una sola vez.
A27: LA PREGUNTA PARA MARLEY
A28: Margen de contribución mensual promedio de un punto Horeca | C28: ← completar con el dato del ERP
A29: Con el presupuesto comprometido, a 24 meses el plan… | B29: =IF(B28="","completar B28",IF(B28>=C24,"se paga","no se paga en este horizonte")) -> completar B28
A30: Con el presupuesto comprometido, a 12 meses el plan… | B30: =IF(B28="","completar B28",IF(B28>=C22,"se paga","no se paga en este horizonte")) -> completar B28
A31: El dato vive en el ERP de Marley y el caso no lo entrega. Convertir la incógnita en una sola pregunta es el aporte de esta hoja: responde en minutos si el plan se justifica.
